pycloudmessenger/__init__.py
pycloudmessenger/rabbitmq.py
pycloudmessenger/serializer.py
pycloudmessenger/utils.py
pycloudmessenger/castor/__init__.py
pycloudmessenger/castor/api_abc.py
pycloudmessenger/castor/castor_rest.py
pycloudmessenger/castor/castorapi.py
pycloudmessenger/castor/message_catalog.py
pycloudmessenger/ffl/__init__.py
pycloudmessenger/ffl/abstractions.py
pycloudmessenger/ffl/fflapi.py
pycloudmessenger/ffl/message_catalog.py
pycloudmessenger-0.8.0.dist-info/LICENSE.txt
pycloudmessenger-0.8.0.dist-info/METADATA
pycloudmessenger-0.8.0.dist-info/WHEEL
pycloudmessenger-0.8.0.dist-info/top_level.txt
pycloudmessenger-0.8.0.dist-info/RECORD
