Metadata-Version: 2.1
Name: pycloudmessenger
Version: 0.8.0
Summary: Package for interacting with messaging based cloud services from IBM Research Ireland
Home-page: https://github.com/IBM/pycloudmessenger
Author: Mark Purcell
Author-email: markpurcell@ie.ibm.com,mkpurcell@yahoo.com
License: Apache 2.0
Requires-Python: >=3.6
License-File: LICENSE.txt
Requires-Dist: pika (>=1.2.0)
Requires-Dist: requests (>=2.18.4)
Requires-Dist: requests-toolbelt
Requires-Dist: clint
Requires-Dist: jsonpickle
Requires-Dist: tenacity
